continuous_eval/__init__.py
continuous_eval/data_downloader.py
continuous_eval/eval/__init__.py
continuous_eval/eval/dataset.py
continuous_eval/eval/logger.py
continuous_eval/eval/modules.py
continuous_eval/eval/pipeline.py
continuous_eval/eval/result_types.py
continuous_eval/eval/runner.py
continuous_eval/eval/tests.py
continuous_eval/eval/types.py
continuous_eval/llms/__init__.py
continuous_eval/llms/anthropic.py
continuous_eval/llms/anthropic_bedrock.py
continuous_eval/llms/azure.py
continuous_eval/llms/azure_openai.py
continuous_eval/llms/base.py
continuous_eval/llms/bedrock.py
continuous_eval/llms/cohere.py
continuous_eval/llms/google.py
continuous_eval/llms/openai.py
continuous_eval/metrics/__init__.py
continuous_eval/metrics/base/__init__.py
continuous_eval/metrics/base/llm.py
continuous_eval/metrics/base/metric.py
continuous_eval/metrics/base/probabilistic.py
continuous_eval/metrics/base/prompt.py
continuous_eval/metrics/base/response_type.py
continuous_eval/metrics/classification/__init__.py
continuous_eval/metrics/classification/classification.py
continuous_eval/metrics/code/__init__.py
continuous_eval/metrics/code/python/__init__.py
continuous_eval/metrics/code/python/code_deterministic_metrics.py
continuous_eval/metrics/code/sql/__init__.py
continuous_eval/metrics/code/sql/deterministic.py
continuous_eval/metrics/code/sql/llm.py
continuous_eval/metrics/code/sql/prompts/sql_correctness_sys.jinja2
continuous_eval/metrics/code/sql/prompts/sql_correctness_user.jinja2
continuous_eval/metrics/custom/__init__.py
continuous_eval/metrics/custom/custom_metric.py
continuous_eval/metrics/custom/custom_metric_sys.jinja2
continuous_eval/metrics/custom/custom_metric_sys_probabilistic.jinja2
continuous_eval/metrics/custom/custom_metric_user.jinja2
continuous_eval/metrics/generation/text/__init__.py
continuous_eval/metrics/generation/text/bert.py
continuous_eval/metrics/generation/text/deterministic.py
continuous_eval/metrics/generation/text/llm_based.py
continuous_eval-0.3.14.post2.dist-info/LICENSE
continuous_eval-0.3.14.post2.dist-info/METADATA
continuous_eval-0.3.14.post2.dist-info/WHEEL
continuous_eval-0.3.14.post2.dist-info/RECORD
