Metadata-Version: 2.1
Name: continuous-eval
Version: 0.3.14.post2
Summary: Open-Source Evaluation for GenAI Applications.
License: Apache-2.0
Author: Yi Zhang
Author-email: yi@relari.ai
Requires-Python: >=3.10,<3.13
Classifier: License :: OSI Approved :: Apache Software License
Classifier: Programming Language :: Python :: 3
Classifier: Programming Language :: Python :: 3.10
Classifier: Programming Language :: Python :: 3.11
Classifier: Programming Language :: Python :: 3.12
Provides-Extra: anthropic
Provides-Extra: azure
Provides-Extra: bedrock
Provides-Extra: cohere
Provides-Extra: google
Provides-Extra: semantic
Requires-Dist: anthropic (>=0.40.0,<0.41.0) ; extra == "anthropic"
Requires-Dist: appdirs (>=1.4.4,<2.0.0)
Requires-Dist: azure-ai-inference (>=1.0.0b6,<2.0.0) ; extra == "azure"
Requires-Dist: boto3 (>=1.35.77,<2.0.0) ; extra == "bedrock"
Requires-Dist: cohere (>=5.13.3,<6.0.0) ; extra == "cohere"
Requires-Dist: google-generativeai (>=0.8.3,<0.9.0) ; extra == "google"
Requires-Dist: jinja2 (>=3.1.4,<4.0.0)
Requires-Dist: json-repair (>=0.31.0,<0.32.0)
Requires-Dist: munkres (>=1.1.4,<2.0.0)
Requires-Dist: nltk (>=3.9.1,<4.0.0)
Requires-Dist: openai (>=1.58.1,<2.0.0)
Requires-Dist: pandas (>=2.2.3,<3.0.0) ; extra == "semantic"
Requires-Dist: posthog (>=3.7.4,<4.0.0)
Requires-Dist: python-dotenv (>=1.0.0,<2.0.0)
Requires-Dist: pyyaml (>=6.0.1,<7.0.0)
Requires-Dist: requests (>=2.31.0,<3.0.0)
Requires-Dist: rouge (>=1.0.1,<2.0.0)
Requires-Dist: scikit-learn (>=1.6.0,<2.0.0)
Requires-Dist: sentence-transformers (>=3.3.1,<4.0.0) ; (python_version >= "3.11" and python_version < "4.0") and (extra == "semantic")
Requires-Dist: sentencepiece (>=0.2.0,<0.3.0) ; extra == "semantic"
Requires-Dist: sqlglot (>=26.0.0,<27.0.0)
Requires-Dist: tenacity (>=8.1.0,<9.0.0)
Requires-Dist: thefuzz (>=0.22.1,<0.23.0)
Requires-Dist: tiktoken (>=0.8.0,<0.9.0)
Requires-Dist: torch (>=2.1.1,<3.0.0) ; (python_version >= "3.11" and python_version < "4.0") and (extra == "semantic")
Requires-Dist: tqdm (>=4.66.1,<5.0.0)
Requires-Dist: transformers (>=4.47.1,<5.0.0) ; extra == "semantic"
